data/data.csv
docs/Manual.pdf
docs/Paper.pdf
src/IPVARboot.py
src/IPVARexample.py
src/IRF_IPVAR.py
src/IRFcreator.py
src/evalpvar.py
src/gapfill.py
src/interactPVAR.py
src/irfpreppvar.py
src/minprctile.py
src/paneldetrend.py
src/paneldiff.py
src/panellag.py
src/util.py
src/vardecomp.py
ipvar-1.0.0.dist-info/METADATA
ipvar-1.0.0.dist-info/WHEEL
ipvar-1.0.0.dist-info/licenses/LICENSE
ipvar-1.0.0.dist-info/RECORD
