Metadata-Version: 2.4
Name: IPVAR
Version: 1.0.0
Summary: Interacted Panel VAR Toolbox
License: LGPL-3.0-or-later
License-File: LICENSE
Keywords: DSGE,Macroeconomic Modeling
Author: Alexei Goumilevski
Author-email: agoumilevski@hotmail.com
Maintainer: Alexei Goumilevski
Maintainer-email: Agoumilevski@hotmail.com
Requires-Python: >=3.10,<4.0
Classifier: Environment :: Console
Classifier: Intended Audience :: Science/Research
Classifier: License :: OSI Approved :: GNU Lesser General Public License v3 or later (LGPLv3+)
Classifier: Natural Language :: English
Classifier: Operating System :: OS Independent
Classifier: Programming Language :: Python
Classifier: Programming Language :: Python :: 3
Classifier: Programming Language :: Python :: 3.10
Classifier: Programming Language :: Python :: 3.11
Classifier: Programming Language :: Python :: 3.12
Classifier: Programming Language :: Python :: 3.13
Classifier: Programming Language :: Python :: 3.14
Classifier: Topic :: Software Development
Requires-Dist: matplotlib (==3.10.0)
Requires-Dist: numpy (==1.26.4)
Requires-Dist: pandas (>=2.1.4,<3.0.0)
Requires-Dist: scipy (>=1.11.4,<2.0.0)
Project-URL: Repository, https://github.com/gumilevskij/IPVAR.git
